LICENSE
MANIFEST.in
README.rst
setup.py
docs/CHANGELOG.rst
src/tests/load_async.py
src/tests/load_pool.py
src/tests/test_async.py
src/tests/test_pool.py
src/tests/test_synchronized.py
src/thread_utils/__init__.py
src/thread_utils/_future.py
src/thread_utils/_gc.py
src/thread_utils/async.py
src/thread_utils/error.py
src/thread_utils/pool.py
src/thread_utils/synchronized.py
src/thread_utils.egg-info/PKG-INFO
src/thread_utils.egg-info/SOURCES.txt
src/thread_utils.egg-info/dependency_links.txt
src/thread_utils.egg-info/top_level.txt