Metadata-Version: 1.1
Name: thread_utils
Version: 1.0.1
Summary: Wrapper of threading module providing Actor interface.
Home-page: https://github.com/wbcchsyn/python-thread_utils
Author: Yoshida Shin
Author-email: wbcchsyn@gmail.com
License: ['Apache License 2.0']
Platform: linux
Platform: unix
Classifier: Development Status :: 4 - Beta
Classifier: Intended Audience :: Developers
Classifier: License :: OSI Approved :: Apache Software License
Classifier: Programming Language :: Python
Classifier: Programming Language :: Python :: 2
Classifier: Programming Language :: Python :: 2.7
Classifier: Programming Language :: Python :: 3
Classifier: Programming Language :: Python :: 3.3
Classifier: Programming Language :: Python :: 3.4
Classifier: Topic :: Software Development
Classifier: Topic :: Software Development :: Libraries
Classifier: Topic :: Software Development :: Libraries :: Python Modules
